discord_llms/__init__.py
discord_llms/bot.py
discord_llms/cli.py
discord_llms/config.py
discord_llms/llm.py
discord_llms/logger.py
discord_llms/types.py
discord_llms/templates/assistant_answer_question.md.jinja
discord_llms/templates/assistant_doc_selection.md.jinja
discord_llms/templates/system_answer_question.md.jinja
discord_llms/templates/system_doc_selection.md.jinja
discord_llms-0.1.0.dist-info/METADATA
discord_llms-0.1.0.dist-info/WHEEL
discord_llms-0.1.0.dist-info/entry_points.txt
discord_llms-0.1.0.dist-info/licenses/LICENSE
discord_llms-0.1.0.dist-info/RECORD
