Metadata-Version: 2.4
Name: discord-llms
Version: 0.1.0
Summary: Discord bot that uses LLMs to help users with documentation
Project-URL: Changelog, https://github.com/S1M0N38/discord-llms.txt/blob/main/CHANGELOG.md
Project-URL: Homepage, https://github.com/S1M0N38/discord-llms.txt
Project-URL: Issues, https://github.com/S1M0N38/discord-llms.txt/issues
Project-URL: Repository, https://github.com/S1M0N38/discord-llms.txt
Author-email: S1M0N38 <bertolottosimone@gmail.com>
License-File: LICENSE
Classifier: License :: OSI Approved :: MIT License
Classifier: Programming Language :: Python :: 3 :: Only
Classifier: Programming Language :: Python :: 3.13
Classifier: Programming Language :: Python :: 3.14
Requires-Python: >=3.13
Requires-Dist: discord-py>=2.4
Requires-Dist: httpx>=0.28
Requires-Dist: jinja2>=3.1
Requires-Dist: openai>=2.15
Requires-Dist: pydantic>=2.10
Requires-Dist: pyyaml>=6
